grabby.py
grabby_cli-1.0.0.dist-info/licenses/LICENSE
grabby_cli-1.0.0.dist-info/METADATA
grabby_cli-1.0.0.dist-info/WHEEL
grabby_cli-1.0.0.dist-info/entry_points.txt
grabby_cli-1.0.0.dist-info/top_level.txt
grabby_cli-1.0.0.dist-info/RECORD
