Metadata-Version: 2.4
Name: grabby-cli
Version: 1.0.0
Summary: A YouTube video/audio downloader with exact titles using yt-dlp.
Home-page: https://github.com/ranveerkavale/grabby
Author: Ranveer
Requires-Python: >=3.7
License-File: LICENSE
Requires-Dist: yt-dlp
Requires-Dist: browser-cookie3
Dynamic: author
Dynamic: home-page
Dynamic: license-file
Dynamic: requires-dist
Dynamic: requires-python
Dynamic: summary
